thunderconfig/__init__.py
thunderconfig/agent_config.py
thunderdome_tools-2.1.1.dist-info/METADATA
thunderdome_tools-2.1.1.dist-info/WHEEL
thunderdome_tools-2.1.1.dist-info/top_level.txt
thunderdome_tools-2.1.1.dist-info/RECORD
