Metadata-Version: 2.1
Name: thunderdome-tools
Version: 2.1.1
Summary: A utility package for standardized API configurations and tools.
Home-page: https://github.com/thunderdomeai/thundertools
Author: Jake Mayer
Author-email: jakemay3r@gmail.com
Classifier: Programming Language :: Python :: 3
Classifier: License :: OSI Approved :: MIT License
Classifier: Operating System :: OS Independent
Requires-Python: >=3.7
Requires-Dist: langchain>=0.0.1
Requires-Dist: typing>=0.0.1
Requires-Dist: datetime>=0.0.1
Requires-Dist: langchain-openai>=0.0.1
Requires-Dist: langchain-anthropic>=0.0.1
Requires-Dist: langchain-ollama>=0.0.1
